youtube_video/__init__.py
youtube_video/core.py
youtube_videos_py-0.0.1.dist-info/METADATA
youtube_videos_py-0.0.1.dist-info/WHEEL
youtube_videos_py-0.0.1.dist-info/top_level.txt
youtube_videos_py-0.0.1.dist-info/RECORD
