Metadata-Version: 2.1
Name: youtube-videos-py
Version: 0.0.1
Summary: search news,videos,weathers from yahoo
Home-page: https://github.com/ditisrmel/yahoo-search
Author: Cheng
Author-email: kimichen2907@gmail.com
License: MIT license
Requires-Python: >=3.11.4
